drink.v
module drink(d,n,q, reset, clk, y);
output reg y;
input d,n,q;    //n=5,d=10,q=25;
input clk;
input reset;
reg [2:0] cst, nst;
parameter S0 = 3'b000,
          S1 = 3'b001,
          S2 = 3'b010,
          S3 = 3'b011,
              S4 = 3'b100,
              S5 = 3'b101,
              S6 = 3'b110;
always @(cst or d or n or q)
 begin
 case (cst)
   S0: if (n== 1'b1 && d==1'b0 && q==1'b0)
            begin
         nst = S1;
             y=1'b0;
            end
      else if(n== 1'b0 && d==1'b1 && q==1'b0)
            begin
            nst=S2;
            y=1'b0;
            end
            else if(n== 1'b0 && d==1'b0 && q==1'b1)
            begin
            nst=S5;
            y=1'b0;
            end
             else
            begin
            nst = cst;
            y=1'b0;
            end
   S1: if (n== 1'b1 && d==1'b0 && q==1'b0)
            begin
         nst = S2;
             y=1'b0;
            end
      else if(n== 1'b0 && d==1'b1 && q==1'b0)
            begin
            nst=S3;
            y=1'b0;
            end
            else if(n== 1'b0 && d==1'b0 && q==1'b1)
            begin
            nst=S6;
            y=1'b0;
            end
             else
            begin
            nst = cst;
            y=1'b0;
            end
   S2:if (n== 1'b1 && d==1'b0 && q==1'b0)
            begin
         nst = S3;
             y=1'b0;
            end
      else if(n== 1'b0 && d==1'b1 && q==1'b0)
            begin
            nst=S4;
            y=1'b0;
            end
            else if(n== 1'b0 && d==1'b0 && q==1'b1)
            begin
            nst=S0;
            y=1'b1;
            end
             else
            begin
            nst = cst;
            y=1'b0;
            end
   S3: if (n== 1'b1 && d==1'b0 && q==1'b0)
            begin
         nst = S4;
             y=1'b0;
            end
      else if(n== 1'b0 && d==1'b1 && q==1'b0)
            begin
            nst=S5;
            y=1'b0;
            end
            else if(n== 1'b0 && d==1'b0 && q==1'b1)
            begin
            nst=S0;
            y=1'b1;
            end
             else
            begin
            nst = cst;
            y=1'b0;
            end
S4: if (n== 1'b1 && d==1'b0 && q==1'b0)
            begin
         nst = S5;
             y=1'b0;
            end
      else if(n== 1'b0 && d==1'b1 && q==1'b0)
            begin
            nst=S6;
            y=1'b0;
            end
            else if(n== 1'b0 && d==1'b0 && q==1'b1)
            begin
            nst=S0;
            y=1'b1;
            end
             else
            begin
            nst = cst;
            y=1'b0;
            end
S5: if (n== 1'b1 && d==1'b0 && q==1'b0)
            begin
         nst = S6;
             y=1'b0;
            end
      else if(n== 1'b0 && d==1'b1 && q==1'b0)
            begin
            nst=S0;
            y=1'b1;
            end
            else if(n== 1'b0 && d==1'b0 && q==1'b1)
            begin
            nst=S0;
            y=1'b1;
            end
             else
            begin
            nst = cst;
            y=1'b0;
            end
S6: if (n== 1'b1 && d==1'b0 && q==1'b0)
            begin
         nst =S0;
             y=1'b1;
            end
      else if(n== 1'b0 && d==1'b1 && q==1'b0)
            begin
            nst=S0;
            y=1'b1;
            end
            else if(n== 1'b0 && d==1'b0 && q==1'b1)
            begin
            nst=S0;
            y=1'b1;
            end
             else
            begin
            nst = cst;
            y=1'b0;
            end
                       
   default: nst = S0;
  endcase
end
always@(posedge clk) //or posedge reset)
begin
 if (reset)
   cst <= S0;
 else
   cst <= nst;
end
endmodule

drink_tb.v
module drink_tb;
reg n,d,q,clk,reset;
wire y;
drink m1(d,n,q,reset, clk, y);
initial
begin
$dumpfile ("tb_vm.vcd");
$dumpvars (0, drink_tb);
end

initial
begin
reset=0;
clk=0;n=0;q=0;d=0;
$monitor($time, , ,"c=%b",clk,,"y=%b",y,,"r=%b",reset,,"d=%b",d,,"n=%b",n,,"q=%b",q);
#10 d=0;n=1;q=0;
#10 d=1;n=0;q=0;
#10 d=1;n=0;q=0;
#10 d=0;n=1;q=0;
#10 d=0;n=1;q=0;
#10 d=0;n=1;q=0;
#10 d=0;n=1;q=0;
#10 d=0;n=1;q=0;
#10 d=0;n=0;q=0;
end
always
#5 clk=~clk;
initial
begin
#100 $finish ;
end
endmodule

tb_vm.vcd
$date
	Sun Nov 21 21:14:52 2021
$end
$version
	Icarus Verilog
$end
$timescale
	1s
$end
$scope module drink_tb $end
$var wire 1 ! y $end
$var reg 1 " clk $end
$var reg 1 # d $end
$var reg 1 $ n $end
$var reg 1 % q $end
$var reg 1 & reset $end
$scope module m1 $end
$var wire 1 " clk $end
$var wire 1 # d $end
$var wire 1 $ n $end
$var wire 1 % q $end
$var wire 1 & reset $end
$var reg 3 ' cst [2:0] $end
$var reg 3 ( nst [2:0] $end
$var reg 1 ! y $end
$upscope $end
$upscope $end
$enddefinitions $end
#0
$dumpvars
b0 (
bx '
0&
0%
0$
0#
0"
x!
$end
#5
0!
b0 '
1"
#10
b1 (
0"
1$
#15
b10 (
b1 '
1"
#20
b11 (
0"
0$
1#
#25
b101 (
b11 '
1"
#30
0"
#35
1!
b0 (
b101 '
1"
#40
0!
b110 (
0"
1$
0#
#45
1!
b0 (
b110 '
1"
#50
0"
#55
0!
b1 (
b0 '
1"
#60
0"
#65
b10 (
b1 '
1"
#70
0"
#75
b11 (
b10 '
1"
#80
0"
#85
b100 (
b11 '
1"
#90
b11 (
0"
0$
